scrapy_rss/VERSION
scrapy_rss/__init__.py
scrapy_rss/elements.py
scrapy_rss/exceptions.py
scrapy_rss/exporters.py
scrapy_rss/items.py
scrapy_rss/pipelines.py
scrapy_rss/utils.py
scrapy_rss/meta/__init__.py
scrapy_rss/meta/attribute.py
scrapy_rss/meta/element.py
scrapy_rss/meta/item.py
scrapy_rss/meta/nscomponent.py
scrapy_rss/rss/__init__.py
scrapy_rss/rss/channel.py
scrapy_rss/rss/channel_elements.py
scrapy_rss/rss/item_elements.py
scrapy_rss/rss/items.py
scrapy_rss/rss/old/__init__.py
scrapy_rss/rss/old/item_elements.py
scrapy_rss/rss/old/items.py
scrapy_rss-1.0.1.dist-info/licenses/LICENSE
scrapy_rss-1.0.1.dist-info/METADATA
scrapy_rss-1.0.1.dist-info/WHEEL
scrapy_rss-1.0.1.dist-info/top_level.txt
scrapy_rss-1.0.1.dist-info/RECORD
