Metadata-Version: 2.1
Name: scrapy-rss
Version: 1.0.1
Summary: RSS Tools for Scrapy Framework
Home-page: https://github.com/woxcab/scrapy_rss
License: BSD
Project-URL: Source, https://github.com/woxcab/scrapy_rss
Project-URL: Tracker, https://github.com/woxcab/scrapy_rss/issues
Platform: UNKNOWN
Classifier: Framework :: Scrapy
Classifier: Development Status :: 5 - Production/Stable
Classifier: Intended Audience :: Developers
Classifier: License :: OSI Approved :: BSD License
Classifier: Operating System :: OS Independent
Classifier: Programming Language :: Python
Classifier: Programming Language :: Python :: 2
Classifier: Programming Language :: Python :: 2.7
Classifier: Programming Language :: Python :: 3
Classifier: Programming Language :: Python :: 3.3
Classifier: Programming Language :: Python :: 3.4
Classifier: Programming Language :: Python :: 3.5
Classifier: Programming Language :: Python :: 3.6
Classifier: Programming Language :: Python :: 3.7
Classifier: Programming Language :: Python :: 3.8
Classifier: Programming Language :: Python :: 3.9
Classifier: Programming Language :: Python :: 3.10
Classifier: Programming Language :: Python :: 3.11
Classifier: Programming Language :: Python :: 3.12
Classifier: Programming Language :: Python :: 3.13
Classifier: Topic :: Internet :: WWW/HTTP
Classifier: Topic :: Software Development :: Libraries :: Python Modules
Requires-Python: >=2.7, !=3.0.*, !=3.1.*, !=3.2.*
Provides-Extra: testing
Requires-Dist: packaging
Requires-Dist: six
Requires-Dist: scrapy (<2.0,>=1.3.1); python_version < "3"
Requires-Dist: python-dateutil; python_version < "3.6"
Requires-Dist: cryptography (<2.0); python_version == "3.3.*"
Requires-Dist: pyOpenSSL (<17.3.0); python_version == "3.3.*"
Requires-Dist: scrapy (<1.5.0); python_version == "3.3.*"
Requires-Dist: scrapy (<1.8.0,>=1.1); python_version == "3.4.*"
Requires-Dist: scrapy (>=1.1); python_version == "3.5.*"
Requires-Dist: scrapy (>=1.3.1); python_version > "3.5"
Requires-Dist: scrapy (>=1.7.1); python_version >= "3.10"
Provides-Extra: testing
Requires-Dist: coverage; extra == 'testing'
Requires-Dist: packaging; extra == 'testing'
Requires-Dist: parameterized; extra == 'testing'
Requires-Dist: pytest; extra == 'testing'
Requires-Dist: pytest-cov; extra == 'testing'
Requires-Dist: pytest-xdist; extra == 'testing'
Requires-Dist: tox; extra == 'testing'
Requires-Dist: xmlunittest; extra == 'testing'
Provides-Extra: testing
Requires-Dist: backports.tempfile; python_version < "3.2" and extra == 'testing'
Provides-Extra: testing
Requires-Dist: enum34; python_version < "3.4" and extra == 'testing'
Provides-Extra: testing
Requires-Dist: pytest-asyncio; python_version >= "3.5" and extra == 'testing'
